setup.cfg
setup.py
api2sshallowedusers/__init__.py
api2sshallowedusers/helpers.py
api2sshallowedusers/server.py
api2sshallowedusers/ssh.py
api2sshallowedusers.egg-info/PKG-INFO
api2sshallowedusers.egg-info/SOURCES.txt
api2sshallowedusers.egg-info/dependency_links.txt
api2sshallowedusers.egg-info/entry_points.txt
api2sshallowedusers.egg-info/requires.txt
api2sshallowedusers.egg-info/top_level.txt