Metadata-Version: 1.1
Name: api2sshallowedusers
Version: 0.0.3
Summary: API to list, add or remove allowed users from sshd_config         and reload daemon accordingly
Home-page: https://github.com/gloutsch/sqreen-test
Author: Gauthier
Author-email: gauthier@louts.ch
License: MIT
Download-URL: https://github.com/gloutsch/sqreen-test/tarball/0.0.3
Keywords: flask ssh allowed users
Platform: UNKNOWN
Classifier: Development Status :: 3 - Alpha
Classifier: Intended Audience :: Developers
Classifier: Topic :: Software Development :: Build Tools
Classifier: License :: OSI Approved :: MIT License
Classifier: Programming Language :: Python :: 3
Classifier: Programming Language :: Python :: 3.3
Classifier: Programming Language :: Python :: 3.4
Classifier: Programming Language :: Python :: 3.5
Classifier: Programming Language :: Python :: 3.6
